pypeline_semantic_release/__init__.py
pypeline_semantic_release/py.typed
pypeline_semantic_release/steps.py
pypeline_semantic_release-0.4.1.dist-info/LICENSE
pypeline_semantic_release-0.4.1.dist-info/METADATA
pypeline_semantic_release-0.4.1.dist-info/WHEEL
pypeline_semantic_release-0.4.1.dist-info/RECORD
