Metadata-Version: 2.3
Name: pypeline-semantic-release
Version: 0.4.1
Summary: Pypeline step for semantic release.
License: MIT
Author: cuinixam
Author-email: me@cuinixam.com
Requires-Python: >=3.10,<4.0
Classifier: Development Status :: 2 - Pre-Alpha
Classifier: Intended Audience :: Developers
Classifier: License :: OSI Approved :: MIT License
Classifier: Natural Language :: English
Classifier: Operating System :: OS Independent
Classifier: Programming Language :: Python :: 3
Classifier: Programming Language :: Python :: 3.10
Classifier: Programming Language :: Python :: 3.11
Classifier: Programming Language :: Python :: 3.12
Classifier: Programming Language :: Python :: 3.13
Classifier: Topic :: Software Development :: Libraries
Requires-Dist: py-app-dev (>=2.7,<3.0)
Requires-Dist: pypeline-runner (>=1.14,<2.0)
Requires-Dist: python-semantic-release (>=9.16,<10.0)
Project-URL: Bug Tracker, https://github.com/cuinixam/pypeline-semantic-release/issues
Project-URL: Changelog, https://github.com/cuinixam/pypeline-semantic-release/blob/main/CHANGELOG.md
Project-URL: Repository, https://github.com/cuinixam/pypeline-semantic-release
